qtoggleserver/pushover/__init__.py
qtoggleserver/pushover/pushovereventhandler.py
qtoggleserver_pushover-1.5.0.dist-info/licenses/LICENSE.txt
qtoggleserver_pushover-1.5.0.dist-info/METADATA
qtoggleserver_pushover-1.5.0.dist-info/WHEEL
qtoggleserver_pushover-1.5.0.dist-info/top_level.txt
qtoggleserver_pushover-1.5.0.dist-info/RECORD
