Metadata-Version: 2.4
Name: qtoggleserver-pushover
Version: 1.5.0
Summary: PushOver notifications for qToggleServer
Author-email: Calin Crisan <ccrisan@gmail.com>
License: Apache 2.0
Requires-Python: >=3.11
License-File: LICENSE.txt
Requires-Dist: aiohttp
Dynamic: license-file
